PolibasePersonReviewAutomationService/__init__.py
PolibasePersonReviewAutomationService/__main__.py
PolibasePersonReviewAutomationService/api.py
PolibasePersonReviewAutomationService/const.py
PolibasePersonReviewAutomationService/service.py
pih_plb_rvw_auto-0.15.dist-info/METADATA
pih_plb_rvw_auto-0.15.dist-info/WHEEL
pih_plb_rvw_auto-0.15.dist-info/entry_points.txt
pih_plb_rvw_auto-0.15.dist-info/top_level.txt
pih_plb_rvw_auto-0.15.dist-info/RECORD
